{
  "IsWild": false,
  "DeckId": 6799385604,
  "Name": "zs",
  "HeroCardId": "HERO_01b",
  "CardIds": [
    "CS2_103",
    "CS2_103",
    "EX1_011",
    "EX1_011",
    "EX1_400",
    "EX1_400",
    "EX1_508",
    "EX1_508",
    "CS2_171",
    "CS2_171",
    "CS2_189",
    "CS2_189",
    "CS1_042",
    "CS1_042",
    "CS2_108",
    "CS2_108",
    "CS2_105",
    "CS2_105",
    "CS2_114",
    "CS2_114",
    "EX1_084",
    "EX1_084",
    "CS2_106",
    "CS2_106",
    "EX1_606",
    "EX1_606",
    "NEW1_011",
    "NEW1_011",
    "CS2_112",
    "CS2_112"
  ]
}